AUTHORS
CHANGES
LICENSE
MANIFEST.in
README.rst
VISIONARY
requirements.txt
setup.py
simpleapi/__init__.py
simpleapi.egg-info/PKG-INFO
simpleapi.egg-info/SOURCES.txt
simpleapi.egg-info/dependency_links.txt
simpleapi.egg-info/not-zip-safe
simpleapi.egg-info/requires.txt
simpleapi.egg-info/top_level.txt
simpleapi/client/__init__.py
simpleapi/client/client.py
simpleapi/client/dummy.py
simpleapi/message/__init__.py
simpleapi/message/common.py
simpleapi/message/extjs.py
simpleapi/message/formatter.py
simpleapi/message/py2xml.py
simpleapi/message/sajson.py
simpleapi/message/wrapper.py
simpleapi/server/__init__.py
simpleapi/server/feature.py
simpleapi/server/namespace.py
simpleapi/server/preformat.py
simpleapi/server/request.py
simpleapi/server/response.py
simpleapi/server/route.py
simpleapi/server/routemgr.py
simpleapi/server/sapirequest.py
simpleapi/server/serializer.py
simpleapi/server/session.py
simpleapi/server/utils.py
tests/__init__.py
tests/formatter_wrapper.py
tests/namespace.py
tests/route.py
tests/settings.py
tests/xml.py