Metadata-Version: 1.0
Name: simpleapi
Version: 0.0.9
Summary: A simple API-framework to provide an easy to use, consistent and portable client/server-architecture (for django, flask and a lot more).
Home-page: http://github.com/flosch/simpleapi/tree/
Author: Florian Schlachter
Author-email: flori@n-schlachter.de
License: UNKNOWN
Platform: UNKNOWN
Classifier: Development Status :: 3 - Alpha
Classifier: Environment :: Web Environment
Classifier: Intended Audience :: Developers
Classifier: License :: OSI Approved :: MIT License
Classifier: Operating System :: OS Independent
Classifier: Programming Language :: Python
